changelogbump/Changelog.py
changelogbump/Metadata.py
changelogbump/PyProject.py
changelogbump/Version.py
changelogbump/__init__.py
changelogbump/app.py
changelogbump/static/header_1.1.0.txt
changelogbump/util.py
changelogbump-0.5.0.dist-info/METADATA
changelogbump-0.5.0.dist-info/WHEEL
changelogbump-0.5.0.dist-info/entry_points.txt
changelogbump-0.5.0.dist-info/RECORD
