Metadata-Version: 2.4
Name: changelogbump
Version: 0.5.0
Summary: A CLI tool to manage project versioning and changelogs with Keep a Changelog compliance.
License-Expression: MIT
Keywords: changelog,versioning,semantic,cli
Author: Andrew Galloway
Author-email: akq.galloway@gmail.com
Requires-Python: >=3.11
Classifier: Development Status :: 3 - Alpha
Classifier: Intended Audience :: Developers
Classifier: License :: OSI Approved :: MIT License
Classifier: Programming Language :: Python :: 3.11
Classifier: Programming Language :: Python :: 3
Classifier: Topic :: Software Development :: Build Tools
Classifier: Topic :: Utilities
Requires-Dist: click (>=8.2.1,<9.0.0)
Requires-Dist: toml (>=0.10.2,<0.11.0)
Project-URL: Homepage, https://github.com/muad-dweeb/changelogbump
